LICENSE
MANIFEST.in
README.md
setup.py
ctpbee/__init__.py
ctpbee/app.py
ctpbee/center.py
ctpbee/cmdline.py
ctpbee/config.py
ctpbee/constant.py
ctpbee/date.py
ctpbee/func.py
ctpbee/helpers.py
ctpbee/level.py
ctpbee/log.py
ctpbee/record.py
ctpbee/signals.py
ctpbee/stream.py
ctpbee.egg-info/PKG-INFO
ctpbee.egg-info/SOURCES.txt
ctpbee.egg-info/dependency_links.txt
ctpbee.egg-info/entry_points.txt
ctpbee.egg-info/not-zip-safe
ctpbee.egg-info/requires.txt
ctpbee.egg-info/top_level.txt
ctpbee/context/__init__.py
ctpbee/context/proxy.py
ctpbee/data_handle/__init__.py
ctpbee/data_handle/local_position.py
ctpbee/exceptions/__init__.py
ctpbee/exceptions/exception.py
ctpbee/indicator/__init__.py
ctpbee/indicator/back.py
ctpbee/indicator/indicator.py
ctpbee/interface/__init__.py
ctpbee/interface/func.py
ctpbee/interface/ctp/__init__.py
ctpbee/interface/ctp/lib.py
ctpbee/interface/ctp/md_api.py
ctpbee/interface/ctp/td_api.py
ctpbee/interface/ctp_mini/__init__.py
ctpbee/interface/ctp_mini/lib.py
ctpbee/interface/ctp_mini/md_api.py
ctpbee/interface/ctp_mini/td_api.py
ctpbee/interface/local/__init__.py
ctpbee/interface/local/market.py
ctpbee/interface/local/trading.py
ctpbee/interface/looper/__init__.py
ctpbee/interface/looper/md_api.py
ctpbee/interface/looper/td_api.py
ctpbee/jsond/__init__.py
ctpbee/jsond/pollen.py
ctpbee/jsond/tag.py
ctpbee/looper/__init__.py
ctpbee/looper/account.py
ctpbee/looper/data.py
ctpbee/looper/interface.py
ctpbee/looper/report.py
ctpbee/looper/templates/base.html
ctpbee/looper/templates/looper.html
ctpbee/looper/templates/trade_record.html