Metadata-Version: 2.2
Name: ctpbee
Version: 1.7.1
Summary: Easy ctp trade and market support
Home-page: https://github.com/ctpbee/ctpbee
Author: somewheve
Author-email: somewheve@gmail.com
License: MIT
Platform: Windows
Platform: Linux
Platform: Mac OS-X
License-File: LICENSE
Requires-Dist: pytz
Requires-Dist: blinker
Requires-Dist: requests
Requires-Dist: simplejson
Requires-Dist: lxml
Requires-Dist: jinja2
Requires-Dist: redis
Requires-Dist: click
Requires-Dist: cologer>=2.0
Requires-Dist: ctpbee_api>=0.40
Requires-Dist: numpy
Requires-Dist: pandas
Requires-Dist: ctpbee_kline
Dynamic: author
Dynamic: author-email
Dynamic: description-content-type
Dynamic: home-page
Dynamic: license
Dynamic: platform
Dynamic: requires-dist
Dynamic: summary
